odoo/addons/barcode_action/README.rst
odoo/addons/barcode_action/__init__.py
odoo/addons/barcode_action/__manifest__.py
odoo/addons/barcode_action/demo/barcode_action_demo.xml
odoo/addons/barcode_action/i18n/barcode_action.pot
odoo/addons/barcode_action/i18n/es.po
odoo/addons/barcode_action/models/__init__.py
odoo/addons/barcode_action/models/res_partner.py
odoo/addons/barcode_action/readme/CONTRIBUTORS.rst
odoo/addons/barcode_action/readme/DESCRIPTION.rst
odoo/addons/barcode_action/readme/USAGE.rst
odoo/addons/barcode_action/static/description/icon.png
odoo/addons/barcode_action/static/description/index.html
odoo/addons/barcode_action/static/src/js/action_barcode_form.js
odoo/addons/barcode_action/static/src/js/action_barcode_widget.js
odoo/addons/barcode_action/tests/__init__.py
odoo/addons/barcode_action/tests/test_partner_find.py
odoo/addons/barcode_action/views/barcode_templates.xml
odoo/addons/barcode_action/wizard/__init__.py
odoo/addons/barcode_action/wizard/barcode_action.py
odoo/addons/barcode_action/wizard/barcode_action_view.xml
odoo11_addon_barcode_action-11.0.1.0.0.99.dev10.dist-info/METADATA
odoo11_addon_barcode_action-11.0.1.0.0.99.dev10.dist-info/WHEEL
odoo11_addon_barcode_action-11.0.1.0.0.99.dev10.dist-info/top_level.txt
odoo11_addon_barcode_action-11.0.1.0.0.99.dev10.dist-info/RECORD
